pdfx/__init__.py
pdfx/__main__.py
pdfx/cli.py
pdfx/main.py
pdfx_tool-0.2.2.dist-info/licenses/LICENSE
pdfx_tool-0.2.2.dist-info/METADATA
pdfx_tool-0.2.2.dist-info/WHEEL
pdfx_tool-0.2.2.dist-info/entry_points.txt
pdfx_tool-0.2.2.dist-info/top_level.txt
pdfx_tool-0.2.2.dist-info/RECORD
