Metadata-Version: 2.4
Name: pdfx-tool
Version: 0.2.2
Summary: A local CLI tool for PDF and image manipulation - merge PDFs, split by page/range, convert images to PDF with enhancement
Home-page: https://pypi.org/project/pdfx-tool/
Author: Manoj Adhikari
Author-email: Manoj Adhikari <adhikarim@etsu.edu>
Maintainer-email: Manoj Adhikari <adhikarim@etsu.edu>
License: MIT
Project-URL: Homepage, https://pypi.org/project/pdfx-tool/
Project-URL: API Documentation, https://github.com/jonamadk/PDF-X/blob/main/API_DOCUMENTATION.md
Project-URL: Repository, https://github.com/jonamadk/PDF-X
Project-URL: Development, https://github.com/jonamadk/PDF-X/blob/main/DEVELOPMENT.md
Project-URL: Issues, https://github.com/jonamadk/pdfx/issues
Keywords: pdf,cli,merge,split,filter,ocr,convert
Classifier: Development Status :: 4 - Beta
Classifier: Intended Audience :: Developers
Classifier: Intended Audience :: End Users/Desktop
Classifier: Operating System :: OS Independent
Classifier: Programming Language :: Python :: 3
Classifier: Programming Language :: Python :: 3.8
Classifier: Programming Language :: Python :: 3.9
Classifier: Programming Language :: Python :: 3.10
Classifier: Programming Language :: Python :: 3.11
Classifier: Programming Language :: Python :: 3.12
Classifier: Topic :: Utilities
Classifier: Topic :: Office/Business
Classifier: Topic :: Multimedia :: Graphics :: Graphics Conversion
Requires-Python: >=3.8
License-File: LICENSE
Requires-Dist: pypdf>=3.0.0
Requires-Dist: cryptography>=41.0.0
Provides-Extra: full
Requires-Dist: pymupdf>=1.22.0; extra == "full"
Requires-Dist: Pillow>=10.0.0; extra == "full"
Requires-Dist: pytesseract>=0.3.10; extra == "full"
Requires-Dist: pdf2image>=1.16.3; extra == "full"
Provides-Extra: dev
Requires-Dist: pytest>=7.0.0; extra == "dev"
Requires-Dist: pytest-cov>=4.0.0; extra == "dev"
Requires-Dist: black>=23.0.0; extra == "dev"
Requires-Dist: flake8>=6.0.0; extra == "dev"
Requires-Dist: mypy>=1.0.0; extra == "dev"
Dynamic: author
Dynamic: home-page
Dynamic: license-file
Dynamic: requires-python
